jk_soccer_core/__init__.py
jk_soccer_core/match.py
jk_soccer_core/calculations/README.md
jk_soccer_core/calculations/__init__.py
jk_soccer_core/calculations/abstract_match_calculation.py
jk_soccer_core/calculations/draws.py
jk_soccer_core/calculations/losses.py
jk_soccer_core/calculations/meetings.py
jk_soccer_core/calculations/percentages.py
jk_soccer_core/calculations/points.py
jk_soccer_core/calculations/wins.py
jk_soccer_core/models/__init__.py
jk_soccer_core/models/coach.py
jk_soccer_core/models/match.py
jk_soccer_core/models/player.py
jk_soccer_core/models/team.py
jk_soccer_core-1.3.0.dist-info/METADATA
jk_soccer_core-1.3.0.dist-info/WHEEL
jk_soccer_core-1.3.0.dist-info/entry_points.txt
jk_soccer_core-1.3.0.dist-info/licenses/LICENSE
jk_soccer_core-1.3.0.dist-info/RECORD
