Metadata-Version: 2.4
Name: jk-soccer-core
Version: 1.3.0
Summary: Add your description here
Author-email: Omar Crosby <omar.crosby@gmail.com>
License-File: LICENSE
Requires-Python: >=3.12
Requires-Dist: marimo
Requires-Dist: matplotlib
Requires-Dist: numpy
Requires-Dist: pandas
Requires-Dist: pydantic
Requires-Dist: toml
